catfishq/__init__.py
catfishq/cat_fastq.py
catfishq-1.3.0.dist-info/LICENSE
catfishq-1.3.0.dist-info/METADATA
catfishq-1.3.0.dist-info/WHEEL
catfishq-1.3.0.dist-info/entry_points.txt
catfishq-1.3.0.dist-info/top_level.txt
catfishq-1.3.0.dist-info/RECORD
