Metadata-Version: 2.1
Name: catfishq
Version: 1.3.0
Summary: Cat FASTQ files
Home-page: UNKNOWN
Author: philres
Author-email: UNKNOWN
License: MIT
Platform: UNKNOWN
Requires-Dist: pysam
